cli_helpers/__init__.py
cli_helpers/compat.py
cli_helpers/config.py
cli_helpers/utils.py
cli_helpers/tabular_output/__init__.py
cli_helpers/tabular_output/delimited_output_adapter.py
cli_helpers/tabular_output/json_output_adapter.py
cli_helpers/tabular_output/output_formatter.py
cli_helpers/tabular_output/preprocessors.py
cli_helpers/tabular_output/tabulate_adapter.py
cli_helpers/tabular_output/tsv_output_adapter.py
cli_helpers/tabular_output/vertical_table_adapter.py
cli_helpers-2.9.0.dist-info/licenses/AUTHORS
cli_helpers-2.9.0.dist-info/licenses/LICENSE
cli_helpers-2.9.0.dist-info/METADATA
cli_helpers-2.9.0.dist-info/WHEEL
cli_helpers-2.9.0.dist-info/top_level.txt
cli_helpers-2.9.0.dist-info/RECORD
