Metadata-Version: 2.4
Name: cli_helpers
Version: 2.9.0
Summary: Helpers for building command-line apps
Home-page: https://github.com/dbcli/cli_helpers
Author: dbcli
Author-email: thomas@roten.us
Classifier: Intended Audience :: Developers
Classifier: License :: OSI Approved :: BSD License
Classifier: Operating System :: Unix
Classifier: Programming Language :: Python
Classifier: Programming Language :: Python :: 3
Classifier: Programming Language :: Python :: 3.6
Classifier: Programming Language :: Python :: 3.7
Classifier: Topic :: Software Development
Classifier: Topic :: Software Development :: Libraries :: Python Modules
Classifier: Topic :: Terminals :: Terminal Emulators/X Terminals
Requires-Python: >=3.6
License-File: LICENSE
License-File: AUTHORS
Requires-Dist: configobj>=5.0.5
Requires-Dist: tabulate[widechars]>=0.9.0
Provides-Extra: styles
Requires-Dist: Pygments>=1.6; extra == "styles"
Dynamic: author
Dynamic: author-email
Dynamic: classifier
Dynamic: description
Dynamic: description-content-type
Dynamic: home-page
Dynamic: license-file
Dynamic: provides-extra
Dynamic: requires-dist
Dynamic: requires-python
Dynamic: summary
